django_charm/__init__.py
django_charm/cli.py
django_charm-0.2.3.dist-info/licenses/LICENSE
django_charm-0.2.3.dist-info/METADATA
django_charm-0.2.3.dist-info/WHEEL
django_charm-0.2.3.dist-info/entry_points.txt
django_charm-0.2.3.dist-info/top_level.txt
django_charm-0.2.3.dist-info/RECORD
