Metadata-Version: 2.4
Name: django-charm
Version: 0.2.3
Summary: Easily create a Django project and app with a single command in seconds.
Requires-Python: >=3.7
License-File: LICENSE
Requires-Dist: django>=4.2
Requires-Dist: requests>=2.31
Dynamic: license-file
